{
    "v": 0.1,
    "id": "",
    "files": {
        "index.ahtml": {
            "filename": "index.ahtml",
            "fileType": "txt",
            "type": "text/html",
            "language": "ahtml",
            "size": 0,
            "truncated": false,
            "content": "<html>\n<head>\n  <!-- Standard Meta -->\n  <meta charset=\"utf-8\" />\n  <meta http-equiv=\"X-UA-Compatible\" content=\"IE=edge,chrome=1\" />\n  <meta name=\"viewport\" content=\"width=device-width, initial-scale=1.0, maximum-scale=1.0\">\n\n  <!-- Site Properties -->\n  <title>Homepage - Semantic</title>\n  <link rel=\"stylesheet\" type=\"text/css\" href=\"https://semantic-ui.com/dist/components/reset.css\">\n  <link rel=\"stylesheet\" type=\"text/css\" href=\"https://semantic-ui.com/dist/components/site.css\">\n\n  <link rel=\"stylesheet\" type=\"text/css\" href=\"https://semantic-ui.com/dist/components/container.css\">\n  <link rel=\"stylesheet\" type=\"text/css\" href=\"https://semantic-ui.com/dist/components/grid.css\">\n  <link rel=\"stylesheet\" type=\"text/css\" href=\"https://semantic-ui.com/dist/components/header.css\">\n  <link rel=\"stylesheet\" type=\"text/css\" href=\"https://semantic-ui.com/dist/components/image.css\">\n  <link rel=\"stylesheet\" type=\"text/css\" href=\"https://semantic-ui.com/dist/components/menu.css\">\n\n  <link rel=\"stylesheet\" type=\"text/css\" href=\"https://semantic-ui.com/dist/components/divider.css\">\n  <link rel=\"stylesheet\" type=\"text/css\" href=\"https://semantic-ui.com/dist/components/dropdown.css\">\n  <link rel=\"stylesheet\" type=\"text/css\" href=\"https://semantic-ui.com/dist/components/segment.css\">\n  <link rel=\"stylesheet\" type=\"text/css\" href=\"https://semantic-ui.com/dist/components/button.css\">\n  <link rel=\"stylesheet\" type=\"text/css\" href=\"https://semantic-ui.com/dist/components/list.css\">\n  <link rel=\"stylesheet\" type=\"text/css\" href=\"https://semantic-ui.com/dist/components/icon.css\">\n  <link rel=\"stylesheet\" type=\"text/css\" href=\"https://semantic-ui.com/dist/components/sidebar.css\">\n  <link rel=\"stylesheet\" type=\"text/css\" href=\"https://semantic-ui.com/dist/components/transition.css\">\n\n  <style type=\"text/css\">\n\n    .hidden.menu {\n      display: none;\n    }\n\n    .masthead.segment {\n      min-height: 700px;\n      padding: 1em 0em;\n    }\n    .masthead .logo.item img {\n      margin-right: 1em;\n    }\n    .masthead .ui.menu .ui.button {\n      margin-left: 0.5em;\n    }\n    .masthead h1.ui.header {\n      margin-top: 3em;\n      margin-bottom: 0em;\n      font-size: 4em;\n      font-weight: normal;\n    }\n    .masthead h2 {\n      font-size: 1.7em;\n      font-weight: normal;\n    }\n\n    .ui.vertical.stripe {\n      padding: 8em 0em;\n    }\n    .ui.vertical.stripe h3 {\n      font-size: 2em;\n    }\n    .ui.vertical.stripe .button + h3,\n    .ui.vertical.stripe p + h3 {\n      margin-top: 3em;\n    }\n    .ui.vertical.stripe .floated.image {\n      clear: both;\n    }\n    .ui.vertical.stripe p {\n      font-size: 1.33em;\n    }\n    .ui.vertical.stripe .horizontal.divider {\n      margin: 3em 0em;\n    }\n\n    .quote.stripe.segment {\n      padding: 0em;\n    }\n    .quote.stripe.segment .grid .column {\n      padding-top: 5em;\n      padding-bottom: 5em;\n    }\n\n    .footer.segment {\n      padding: 5em 0em;\n    }\n\n    .secondary.pointing.menu .toc.item {\n      display: none;\n    }\n\n    @media only screen and (max-width: 700px) {\n      .ui.fixed.menu {\n        display: none !important;\n      }\n      .secondary.pointing.menu .item,\n      .secondary.pointing.menu .menu {\n        display: none;\n      }\n      .secondary.pointing.menu .toc.item {\n        display: block;\n      }\n      .masthead.segment {\n        min-height: 350px;\n      }\n      .masthead h1.ui.header {\n        font-size: 2em;\n        margin-top: 1.5em;\n      }\n      .masthead h2 {\n        margin-top: 0.5em;\n        font-size: 1.5em;\n      }\n    }\n\n\n  </style>\n\n  <script src=\"https://semantic-ui.com/examples/assets/library/jquery.min.js\"></script>\n  <script src=\"https://semantic-ui.com/dist/components/visibility.js\"></script>\n  <script src=\"https://semantic-ui.com/dist/components/sidebar.js\"></script>\n  <script src=\"https://semantic-ui.com/dist/components/transition.js\"></script>\n  <script>\n  $(document)\n    .ready(function() {\n\n      $('.masthead')\n        .visibility({\n          once: false,\n          onBottomPassed: function() {\n            $('.fixed.menu').transition('fade in');\n          },\n          onBottomPassedReverse: function() {\n            $('.fixed.menu').transition('fade out');\n          }\n        })\n      ;\n\n      $('.ui.sidebar')\n        .sidebar('attach events', '.toc.item')\n      ;\n\n    })\n  ;\n  </script>\n</head>\n<body>\n<div>\n<!-- Following Menu -->\n<div class=\"ui large top fixed hidden menu\">\n  <div class=\"ui container\">\n    <a class=\"active item\">Home</a>\n    <a class=\"item\">Work</a>\n    <a class=\"item\">Company</a>\n    <a class=\"item\">Careers</a>\n    <div class=\"right menu\">\n      <div class=\"item\">\n        <a class=\"ui button\">Log in</a>\n      </div>\n      <div class=\"item\">\n        <a class=\"ui primary button\">Sign Up</a>\n      </div>\n    </div>\n  </div>\n</div>\n\n<!-- Sidebar Menu -->\n<div class=\"ui vertical inverted sidebar menu\">\n  <a class=\"active item\">Home</a>\n  <a class=\"item\">Work</a>\n  <a class=\"item\">Company</a>\n  <a class=\"item\">Careers</a>\n  <a class=\"item\">Login</a>\n  <a class=\"item\">Signup</a>\n</div>\n\n<div class=\"pusher\">\n  <div class=\"ui inverted vertical masthead center aligned segment\">\n\n    <div class=\"ui container\">\n      <div class=\"ui large secondary inverted pointing menu\">\n        <a class=\"toc item\">\n          <i class=\"sidebar icon\"></i>\n        </a>\n        <a class=\"active item\">Home</a>\n        <a class=\"item\">Work</a>\n        <a class=\"item\">Company</a>\n        <a class=\"item\">Careers</a>\n        <div class=\"right item\">\n          <a class=\"ui inverted button\">Log in</a>\n          <a class=\"ui inverted button\">Sign Up</a>\n        </div>\n      </div>\n    </div>\n\n    <div class=\"ui text container\">\n      <h1 class=\"ui inverted header\">\n        Imagine-a-Company\n      </h1>\n      <h2>Do whatever you want when you want to.</h2>\n      <div class=\"ui huge primary button\">Get Started <i class=\"right arrow icon\"></i></div>\n    </div>\n\n  </div>\n\n  <div class=\"ui vertical stripe segment\">\n    <div class=\"ui middle aligned stackable grid container\">\n      <div class=\"row\">\n        <div class=\"eight wide column\">\n          <h3 class=\"ui header\">We Help Companies and Companions</h3>\n          <p>We can give your company superpowers to do things that they never thought possible. Let us delight your customers and empower your needs...through pure data analytics.</p>\n          <h3 class=\"ui header\">We Make Bananas That Can Dance</h3>\n          <p>Yes that's right, you thought it was the stuff of dreams, but even bananas can be bioengineered.</p>\n        </div>\n        <div class=\"six wide right floated column\">\n          <img src=\"https://semantic-ui.com/examples/assets/images/wireframe/white-image.png\" class=\"ui large bordered rounded image\">\n        </div>\n      </div>\n      <div class=\"row\">\n        <div class=\"center aligned column\">\n          <a class=\"ui huge button\">Check Them Out</a>\n        </div>\n      </div>\n    </div>\n  </div>\n\n\n  <div class=\"ui vertical stripe quote segment\">\n    <div class=\"ui equal width stackable internally celled grid\">\n      <div class=\"center aligned row\">\n        <div class=\"column\">\n          <h3>\"What a Company\"</h3>\n          <p>That is what they all say about us</p>\n        </div>\n        <div class=\"column\">\n          <h3>\"I shouldn't have gone with their competitor.\"</h3>\n          <p>\n            <img src=\"https://semantic-ui.com/examples/assets/images/avatar/nan.jpg\" class=\"ui avatar image\"> <b>Nan</b> Chief Fun Officer Acme Toys\n          </p>\n        </div>\n      </div>\n    </div>\n  </div>\n\n  <div class=\"ui vertical stripe segment\">\n    <div class=\"ui text container\">\n      <h3 class=\"ui header\">Breaking The Grid, Grabs Your Attention</h3>\n      <p>Instead of focusing on content creation and hard work, we have learned how to master the art of doing nothing by providing massive amounts of whitespace and generic content that can seem massive, monolithic and worth your attention.</p>\n      <a class=\"ui large button\">Read More</a>\n      <h4 class=\"ui horizontal header divider\">\n        <a href=\"#\">Case Studies</a>\n      </h4>\n      <h3 class=\"ui header\">Did We Tell You About Our Bananas?</h3>\n      <p>Yes I know you probably disregarded the earlier boasts as non-sequitur filler content, but its really true. It took years of gene splicing and combinatory DNA research, but our bananas can really dance.</p>\n      <a class=\"ui large button\">I'm Still Quite Interested</a>\n    </div>\n  </div>\n\n\n  <div class=\"ui inverted vertical footer segment\">\n    <div class=\"ui container\">\n      <div class=\"ui stackable inverted divided equal height stackable grid\">\n        <div class=\"three wide column\">\n          <h4 class=\"ui inverted header\">About</h4>\n          <div class=\"ui inverted link list\">\n            <a href=\"#\" class=\"item\">Sitemap</a>\n            <a href=\"#\" class=\"item\">Contact Us</a>\n            <a href=\"#\" class=\"item\">Religious Ceremonies</a>\n            <a href=\"#\" class=\"item\">Gazebo Plans</a>\n          </div>\n        </div>\n        <div class=\"three wide column\">\n          <h4 class=\"ui inverted header\">Services</h4>\n          <div class=\"ui inverted link list\">\n            <a href=\"#\" class=\"item\">Banana Pre-Order</a>\n            <a href=\"#\" class=\"item\">DNA FAQ</a>\n            <a href=\"#\" class=\"item\">How To Access</a>\n            <a href=\"#\" class=\"item\">Favorite X-Men</a>\n          </div>\n        </div>\n        <div class=\"seven wide column\">\n          <h4 class=\"ui inverted header\">Footer Header</h4>\n          <p>Extra space for a call to action inside the footer that could help re-engage users.</p>\n        </div>\n      </div>\n    </div>\n  </div>\n</div>\n</div>\n</body>\n\n</html>",
            "description": ""
        }
    },
    "public": true,
    "createdTime": 1589111576120,
    "lastUpdatedTime": 1589116819318,
    "description": "",
    "projectName": "new project"
}